pandasschemaster/__init__.py
pandasschemaster/base_schema.py
pandasschemaster/schema_column.py
pandasschemaster/schema_dataframe.py
pandasschemaster/schema_generator.py
pandasschemaster-1.0.2.dist-info/licenses/LICENSE
pandasschemaster-1.0.2.dist-info/METADATA
pandasschemaster-1.0.2.dist-info/WHEEL
pandasschemaster-1.0.2.dist-info/top_level.txt
pandasschemaster-1.0.2.dist-info/RECORD
