Metadata-Version: 2.4
Name: pandasschemaster
Version: 1.0.2
Summary: Type-safe DataFrame library with schema validation for pandas
Home-page: https://github.com/gzocche/PandasSchemaster
Author: gzocche
Author-email: Your Name <your.email@example.com>
License-Expression: MIT
Project-URL: Homepage, https://github.com/gzocche/PandasSchemaster
Project-URL: Repository, https://github.com/gzocche/PandasSchemaster
Project-URL: Issues, https://github.com/gzocche/PandasSchemaster/issues
Keywords: pandas,dataframe,schema,validation,type-safety
Classifier: Development Status :: 5 - Production/Stable
Classifier: Intended Audience :: Developers
Classifier: Intended Audience :: Science/Research
Classifier: Operating System :: OS Independent
Classifier: Programming Language :: Python :: 3
Classifier: Programming Language :: Python :: 3.8
Classifier: Programming Language :: Python :: 3.9
Classifier: Programming Language :: Python :: 3.10
Classifier: Programming Language :: Python :: 3.11
Classifier: Programming Language :: Python :: 3.12
Classifier: Programming Language :: Python :: 3.13
Classifier: Topic :: Scientific/Engineering
Classifier: Topic :: Software Development :: Libraries :: Python Modules
Requires-Python: >=3.8
License-File: LICENSE
Requires-Dist: pandas>=2.0.0
Requires-Dist: numpy>=1.24.0
Dynamic: author
Dynamic: home-page
Dynamic: license-file
Dynamic: requires-python
